Metadata-Version: 2.1
Name: conkit
Version: 0.13.3
Summary: Python Interface for Residue-Residue Contact Predictions
Home-page: http://www.conkit.org/en/latest/
Author: Felix Simkovic
Author-email: felixsimkovic@me.com
License: BSD License
Platform: POSIX
Platform: Mac OS
Platform: Windows
Platform: Unix
Classifier: Development Status :: 4 - Beta
Classifier: Intended Audience :: Science/Research
Classifier: License :: OSI Approved :: BSD License
Classifier: Operating System :: OS Independent
Classifier: Programming Language :: Python
Classifier: Programming Language :: Python :: 3.7
Classifier: Programming Language :: Python :: 3.8
Classifier: Programming Language :: Python :: 3.9
Classifier: Topic :: Scientific/Engineering :: Bio-Informatics
License-File: LICENSE.txt
